labrador/__init__.py
labrador/_approach.py
labrador/_project.py
labrador/_work_package.py
labrador/cli.py
labrador/decorators.py
labrador/documentation.py
labrador/errors.py
labrador/utils.py
labrador_assistant-0.1.0.dist-info/METADATA
labrador_assistant-0.1.0.dist-info/WHEEL
labrador_assistant-0.1.0.dist-info/entry_points.txt
labrador_assistant-0.1.0.dist-info/top_level.txt
labrador_assistant-0.1.0.dist-info/RECORD
