Metadata-Version: 2.1
Name: labrador-assistant
Version: 0.1.0
Summary: Your lab assistant keeping your research organized
Home-page: https://gitlab.com/cm-res-dev/labrador
Author: Calixte Mayoraz
Classifier: Programming Language :: Python :: 3
Classifier: Operating System :: OS Independent
Requires-Python: >=3.7
Requires-Dist: mdutils==1.6.0
Requires-Dist: mkdocs==1.6.0
Requires-Dist: pytoml==0.1.21
Requires-Dist: PyYAML==6.0.1
Requires-Dist: rich==13.7.1
Requires-Dist: typer==0.12.3
Requires-Dist: typing-extensions==4.12.1
Requires-Dist: Unidecode==1.3.8
